loom/__init__.py
loom/__main__.py
loom/cli/__init__.py
loom/cli/cli.py
loom/common/activity.py
loom/common/config.py
loom/common/errors.py
loom/common/workflow.py
loom/core/__init__.py
loom/core/compiled.py
loom/core/context.py
loom/core/engine.py
loom/core/graph.py
loom/core/handle.py
loom/core/logger.py
loom/core/runner.py
loom/core/state.py
loom/core/worker.py
loom/core/workflow.py
loom/database/__init__.py
loom/database/db.py
loom/decorators/__init__.py
loom/decorators/activity.py
loom/decorators/workflow.py
loom/lib/progress.py
loom/lib/utils.py
loom/migrations/down/001_setup_pragma.sql
loom/migrations/down/002_create_workflows.sql
loom/migrations/down/003.create_events.sql
loom/migrations/down/004.create_tasks.sql
loom/migrations/down/005.create_indexes.sql
loom/migrations/down/006_auto_update_triggers.sql
loom/migrations/down/007_create_logs.sql
loom/migrations/up/001_setup_pragma.sql
loom/migrations/up/002_create_workflows.sql
loom/migrations/up/003_create_events.sql
loom/migrations/up/004_create_tasks.sql
loom/migrations/up/005_create_indexes.sql
loom/migrations/up/006_auto_update_triggers.sql
loom/migrations/up/007_create_logs.sql
loom/schemas/__init__.py
loom/schemas/activity.py
loom/schemas/database.py
loom/schemas/events.py
loom/schemas/graph.py
loom/schemas/tasks.py
loom/schemas/workflow.py
loom/web/__init__.py
loom/web/main.py
loom/web/schemas.py
loom/web/api/__init__.py
loom/web/api/events.py
loom/web/api/graphs.py
loom/web/api/logs.py
loom/web/api/stats.py
loom/web/api/tasks.py
loom/web/api/workflows.py
loom/web/dist/index.html
loom/web/dist/vite.svg
loom/web/dist/assets/index-CKj6DvD9.css
loom/web/dist/assets/index-Vavv5UoS.js
loom_core-1.5.0.dist-info/licenses/LICENSE
loom_core-1.5.0.dist-info/METADATA
loom_core-1.5.0.dist-info/WHEEL
loom_core-1.5.0.dist-info/entry_points.txt
loom_core-1.5.0.dist-info/top_level.txt
loom_core-1.5.0.dist-info/RECORD
