Metadata-Version: 2.4
Name: loom-core
Version: 1.5.0
Summary: Durable workflow orchestration engine for Python
Home-page: https://github.com/satadeep3927/loom
Author: Satadeep Dasgupta
Author-email: Satadeep Dasgupta <satadeep.dasgupta@brainiuminfotech.com>
License: MIT
Project-URL: Homepage, https://github.com/satadeep3927/loom
Project-URL: Documentation, https://github.com/satadeep3927/loom/blob/main/README.md
Project-URL: Repository, https://github.com/satadeep3927/loom
Project-URL: Issues, https://github.com/satadeep3927/loom/issues
Keywords: workflow,orchestration,durable,event-sourcing,temporal
Classifier: Development Status :: 3 - Alpha
Classifier: Intended Audience :: Developers
Classifier: Topic :: Software Development :: Libraries :: Application Frameworks
Classifier: License :: OSI Approved :: MIT License
Classifier: Programming Language :: Python :: 3
Classifier: Programming Language :: Python :: 3.12
Classifier: Framework :: AsyncIO
Requires-Python: >=3.12
License-File: LICENSE
Requires-Dist: aiosqlite>=0.19.0
Requires-Dist: click>=8.0.0
Requires-Dist: rich>=14.3.1
Requires-Dist: fastapi[standard]>=0.95.0
Requires-Dist: uvicorn[standard]>=0.22.0
Requires-Dist: pydantic>=2.0.0
Provides-Extra: dev
Requires-Dist: pytest>=7.0.0; extra == "dev"
Requires-Dist: pytest-asyncio>=0.21.0; extra == "dev"
Requires-Dist: pytest-cov>=4.0.0; extra == "dev"
Requires-Dist: mypy>=1.0.0; extra == "dev"
Requires-Dist: black>=23.0.0; extra == "dev"
Requires-Dist: isort>=5.12.0; extra == "dev"
Requires-Dist: ruff>=0.1.0; extra == "dev"
Dynamic: author
Dynamic: home-page
Dynamic: license-file
Dynamic: requires-python
